zerophone.py
zerophone-0.0.5.dist-info/DESCRIPTION.rst
zerophone-0.0.5.dist-info/METADATA
zerophone-0.0.5.dist-info/RECORD
zerophone-0.0.5.dist-info/WHEEL
zerophone-0.0.5.dist-info/entry_points.txt
zerophone-0.0.5.dist-info/metadata.json
zerophone-0.0.5.dist-info/top_level.txt
