Metadata-Version: 2.0
Name: zerophone
Version: 0.0.5
Summary: ZeroPhone API library, with CLI
Home-page: https://github.com/ZeroPhone/Zerophone-API-Python
Author: CRImier
Author-email: crimier@yandex.ru
License: UNKNOWN
Download-URL: https://github.com/ZeroPhone/zerophone-api-python/archive/0.0.5.tar.gz
Platform: UNKNOWN
Requires-Dist: jsonrpclib-pelix
